{
    "href": "https://api.spotify.com/v1/users/127486916/playlists/4VuN9vLHkJoQXMR59FVfux/tracks?offset=0&limit=100",
    "items": [
        {
            "artist_id": "64CuUOOirKmdAYLQSfaOyr",
            "artist_name": "The Emotions",
            "popularity": 59,
            "preview_url": "https://p.scdn.co/mp3-preview/e20c1aaa3a9cd0654d3315b31cf9d7079f244d63",
            "track_id": "6UjlpJhUqOQqv0hrb38IDI",
            "track_name": "Best of My Love"
        },
        {
            "artist_id": "38h03gA85YYPeDPd9ER9rT",
            "artist_name": "The O'Jays",
            "popularity": 44,
            "preview_url": "https://p.scdn.co/mp3-preview/165c74a3da185a1da5d195ec499b32877fe42998",
            "track_id": "1xz2x28NqMFRSx4IfJkC5p",
            "track_name": "For the Love of Money"
        },
        {
            "artist_id": "5me0Irg2ANcsgc93uaYrpb",
            "artist_name": "The Notorious B.I.G.",
            "popularity": 47,
            "preview_url": "https://p.scdn.co/mp3-preview/f1f4eac8bf5857d657f3319b90f693bfbeaecc26",
            "track_id": "2XncSBceg7BwEpbWVI6FLi",
            "track_name": "Mo Money Mo Problems (feat. Mase & Puff Daddy)"
        },
        {
            "artist_id": "2siHvYaxjaW5rKVRiIrMYH",
            "artist_name": "Anastacia",
            "popularity": 10,
            "preview_url": "https://p.scdn.co/mp3-preview/01b39a511f12976680fcd673876f59edb225a0d6",
            "track_id": "5V9gvLlsPdgY8Xi3Wa0DCN",
            "track_name": "I'm Outta Love"
        },
        {
            "artist_id": "2eogQKWWoohI3BSnoG7E2U",
            "artist_name": "Donna Summer",
            "popularity": 49,
            "preview_url": "https://p.scdn.co/mp3-preview/0009da117d6c88d36147d521c8903f86ee80bd7d",
            "track_id": "3ZKQVyxT4Jg2lLZRLs7Vgo",
            "track_name": "Bad Girls"
        },
        {
            "artist_id": "3fMbdgg4jU18AjLCKBhRSm",
            "artist_name": "Michael Jackson",
            "popularity": 71,
            "preview_url": "https://p.scdn.co/mp3-preview/575230ca230ab7a79f1b2980e303d7f1612073f3",
            "track_id": "5lA3pwMkBdd24StM90QrNR",
            "track_name": "P.Y.T. (Pretty Young Thing)"
        },
        {
            "artist_id": "2iE18Oxc8YSumAU232n4rW",
            "artist_name": "The Jackson 5",
            "popularity": 64,
            "preview_url": "https://p.scdn.co/mp3-preview/9503603f0b9a1fb95343fb85ca97edc1650c52db",
            "track_id": "3tSi6iFO9yLGIYIqMEgjC9",
            "track_name": "I Want You Back"
        },
        {
            "artist_id": "0TImkz4nPqjegtVSMZnMRq",
            "artist_name": "TLC",
            "popularity": 9,
            "preview_url": null,
            "track_id": "3LSmmLYMtVcV7OgHLoZ9Z8",
            "track_name": "Waterfalls - Single Edit"
        },
        {
            "artist_id": "7guDJrEfX3qb6FEbdPA5qi",
            "artist_name": "Stevie Wonder",
            "popularity": 49,
            "preview_url": "https://p.scdn.co/mp3-preview/0a7b34234cf0fbbd0e3963b4ce83832cee1e78e5",
            "track_id": "3WGaUa5pfM8vPMYhYplWL4",
            "track_name": "Isn't She Lovely"
        },
        {
            "artist_id": "4Otx4bRLSfpah5kX8hdgDC",
            "artist_name": "Naughty By Nature",
            "popularity": 58,
            "preview_url": "https://p.scdn.co/mp3-preview/d8c8340cd0c1850428711c5d4dffe0ead349b0b7",
            "track_id": "4piae89WoVnwucdJzWrB7M",
            "track_name": "O.P.P."
        },
        {
            "artist_id": "7crPfGd2k81ekOoSqQKWWz",
            "artist_name": "Stevie Nicks",
            "popularity": 38,
            "preview_url": "https://p.scdn.co/mp3-preview/3f84a30c847afd09f63ab16faeb2a2f7cb13151c",
            "track_id": "3OeHBpJwMsIGcdumxCtzte",
            "track_name": "Edge of Seventeen"
        },
        {
            "artist_id": "3iQM78Xg0wJnGZhgVNLPmY",
            "artist_name": "McFadden & Whitehead",
            "popularity": 49,
            "preview_url": "https://p.scdn.co/mp3-preview/13c81391c1b2081ddc5de1b570d41041dcadba8d",
            "track_id": "6EOdY7I7Xm1vPP1cyaGbWZ",
            "track_name": "Ain't No Stoppin' Us Now"
        },
        {
            "artist_id": "1ii6e2pv8VIRwnTER71rMl",
            "artist_name": "A Taste Of Honey",
            "popularity": 48,
            "preview_url": "https://p.scdn.co/mp3-preview/d0986e4760796289476afa4e4c72ec1e1ee199a3",
            "track_id": "0y0QpmcF1G3F79rjk3fjUx",
            "track_name": "Boogie Oogie Oogie - Digitally Remastered 99"
        },
        {
            "artist_id": "5m8H6zSadhu1j9Yi04VLqD",
            "artist_name": "Sly & The Family Stone",
            "popularity": 35,
            "preview_url": "https://p.scdn.co/mp3-preview/07d6034fee117c80c4e6924acfce2d09d0071de7",
            "track_id": "6q701mead1QEHZdRiTsGCe",
            "track_name": "Dance to the Music"
        },
        {
            "artist_id": "5SMVzTJyKFJ7TUb46DglcH",
            "artist_name": "Parliament",
            "popularity": 47,
            "preview_url": "https://p.scdn.co/mp3-preview/62c131335d0c3fbc5fc99c778178cc2f42d6c7c5",
            "track_id": "6VSm4HuSiOGWjbt6zpPnvh",
            "track_name": "Flashlight"
        },
        {
            "artist_id": "3koiLjNrgRTNbOwViDipeA",
            "artist_name": "Marvin Gaye",
            "popularity": 55,
            "preview_url": "https://p.scdn.co/mp3-preview/96f9890c57432c7a35dad5d224d25b37f1ba907f",
            "track_id": "6rrUcrhWlW3CqGYT0zxYlz",
            "track_name": "Got To Give It Up (Part 1)"
        },
        {
            "artist_id": "5m8H6zSadhu1j9Yi04VLqD",
            "artist_name": "Sly & The Family Stone",
            "popularity": 4,
            "preview_url": "https://p.scdn.co/mp3-preview/bb0bc55668eac7572f38483ee9d2c09869803961",
            "track_id": "6kdjd3IBSIjMWZEm5BFzNH",
            "track_name": "I Want to Take You Higher"
        },
        {
            "artist_id": "3MdG05syQeRYPPcClLaUGl",
            "artist_name": "Diana Ross",
            "popularity": 47,
            "preview_url": "https://p.scdn.co/mp3-preview/41d6bd17ff513009be99c2f751ccbe67470cbf0a",
            "track_id": "3SnGymj6ijE2iuUfWxLo1q",
            "track_name": "I'm Coming Out"
        },
        {
            "artist_id": "0Xf8oDAJYd2D0k3NLI19OV",
            "artist_name": "CHIC",
            "popularity": 60,
            "preview_url": "https://p.scdn.co/mp3-preview/8dc61ff9b917f8a52ab01ec8bf02f54470664321",
            "track_id": "6Lphpr9Z6H282Sguw0dUWa",
            "track_name": "Le Freak - Single Edit"
        },
        {
            "artist_id": "4QQgXkCYTt3BlENzhyNETg",
            "artist_name": "Earth, Wind & Fire",
            "popularity": 2,
            "preview_url": null,
            "track_id": "2zURg1MjSDNvxHWxDVXGvj",
            "track_name": "September"
        },
        {
            "artist_id": "3koiLjNrgRTNbOwViDipeA",
            "artist_name": "Marvin Gaye",
            "popularity": 63,
            "preview_url": "https://p.scdn.co/mp3-preview/68f7099bfd9995d4f2d611d5fc1f16cb6d8bfa83",
            "track_id": "0jHkgTtTaqg5LNCiYDQPUB",
            "track_name": "Let's Get It On"
        },
        {
            "artist_id": "4nJ3J7RwgYmMARNAVrFb06",
            "artist_name": "The Blackbyrds",
            "popularity": 33,
            "preview_url": "https://p.scdn.co/mp3-preview/312de87150ac8f43b020eab4f8d6db238673bad5",
            "track_id": "65vssm44ghOVf4tBZMY2AE",
            "track_name": "Walking In Rhythm"
        },
        {
            "artist_id": "1b1N51wmSK0ckxFAMPSSHO",
            "artist_name": "The Impressions",
            "popularity": 13,
            "preview_url": "https://p.scdn.co/mp3-preview/6959199675d521d90cfb722b474eeb189eaaabb8",
            "track_id": "62PQXBFeAgS3iUseNRVPpF",
            "track_name": "It's All Right"
        },
        {
            "artist_id": "3koiLjNrgRTNbOwViDipeA",
            "artist_name": "Marvin Gaye",
            "popularity": 68,
            "preview_url": "https://p.scdn.co/mp3-preview/2688ebb604b4efacd0d6e12bf378a8eaa56138a8",
            "track_id": "3VZmChrnVW8JK6ano4gSED",
            "track_name": "Sexual Healing"
        },
        {
            "artist_id": "293zczrfYafIItmnmM3coR",
            "artist_name": "Chuck Berry",
            "popularity": 32,
            "preview_url": "https://p.scdn.co/mp3-preview/c67eb96645211325f58d960e8deb37a38cb65945",
            "track_id": "1pts1Iq4O6NtTKNzNImkLk",
            "track_name": "Brown Eyed Handsome Man - Single Version"
        },
        {
            "artist_id": "36QJpDe2go2KgaRleHCDTp",
            "artist_name": "Led Zeppelin",
            "popularity": 71,
            "preview_url": "https://p.scdn.co/mp3-preview/ce11b19a4d2de9976d7626df0717d0073863909c",
            "track_id": "0hCB0YR03f6AmQaHbwWDe8",
            "track_name": "Whole Lotta Love"
        },
        {
            "artist_id": "3oDbviiivRWhXwIE8hxkVV",
            "artist_name": "The Beach Boys",
            "popularity": 38,
            "preview_url": "https://p.scdn.co/mp3-preview/30277ae410797fd700e5bab9a38053adc9fb59ce",
            "track_id": "4HeznvZhuaqT4TAUNQAZOT",
            "track_name": "Surfer Girl"
        },
        {
            "artist_id": "3koiLjNrgRTNbOwViDipeA",
            "artist_name": "Marvin Gaye",
            "popularity": 35,
            "preview_url": "https://p.scdn.co/mp3-preview/a10cacbb90d2912e6be2d91c7c9c42ab66c788a2",
            "track_id": "4HCKl05ZpdAyijz1pCLQAm",
            "track_name": "Keep Gettin' It On"
        },
        {
            "artist_id": "6j2HWcd7z61iTLbi8eD0hA",
            "artist_name": "Eddy Grant",
            "popularity": 56,
            "preview_url": "https://p.scdn.co/mp3-preview/4759f7d11a7dd5b9ad5d39cd898e7d4c0403c929",
            "track_id": "4cqUq7n3ad0DhJ2JCVw34v",
            "track_name": "Electric Avenue"
        },
        {
            "artist_id": "5cIS9VdHDj2fozLl19Gg2A",
            "artist_name": "Barbara Acklin",
            "popularity": 8,
            "preview_url": null,
            "track_id": "64ixHKi3MfMUMiXDytSalt",
            "track_name": "Am I The Same Girl?"
        },
        {
            "artist_id": "5tTsrGPwQRWUsHR2Xf7Ke9",
            "artist_name": "Natalie Cole",
            "popularity": 66,
            "preview_url": "https://p.scdn.co/mp3-preview/5c5285b2729a76d49717b49b4f36770ea93c1d2e",
            "track_id": "241RmK77gecJ1y7jOoQ5lu",
            "track_name": "This Will Be (An Everlasting Love) - 2003 Digital Remaster"
        },
        {
            "artist_id": "7guDJrEfX3qb6FEbdPA5qi",
            "artist_name": "Stevie Wonder",
            "popularity": 62,
            "preview_url": "https://p.scdn.co/mp3-preview/85ddf7b835e7804d5a5e6839e216b4188ed450b3",
            "track_id": "4kP69y3GKHi9tXckfgp4bK",
            "track_name": "For Once In My Life"
        },
        {
            "artist_id": "3fMbdgg4jU18AjLCKBhRSm",
            "artist_name": "Michael Jackson",
            "popularity": 70,
            "preview_url": "https://p.scdn.co/mp3-preview/a1fb1d7a91cf63421b8da76ed33e4fee7518ccca",
            "track_id": "0S5EEpFAHcT7cm5XOASc29",
            "track_name": "Love Never Felt so Good"
        },
        {
            "artist_id": "3fMbdgg4jU18AjLCKBhRSm",
            "artist_name": "Michael Jackson",
            "popularity": 57,
            "preview_url": "https://p.scdn.co/mp3-preview/b61d9bdc7d511d1f0bc8cc11065a44d1bc9748e4",
            "track_id": "1uCbb7fkxRUrQAvCQgmSHo",
            "track_name": "Wanna Be Startin' Somethin'"
        },
        {
            "artist_id": "7xGGqA85UIWX1GoTVM4itC",
            "artist_name": "The Staple Singers",
            "popularity": 42,
            "preview_url": "https://p.scdn.co/mp3-preview/f79fb05de1baf01908e20409bcb92758232914fb",
            "track_id": "1YQIOrrOg1UDqZCGcZWQ0a",
            "track_name": "Let's Do it Again"
        },
        {
            "artist_id": "3fMbdgg4jU18AjLCKBhRSm",
            "artist_name": "Michael Jackson",
            "popularity": 74,
            "preview_url": "https://p.scdn.co/mp3-preview/01ca80f1b2042f7e4a6d45b5f11bf03060a41c2d",
            "track_id": "48td6xvpokdYwvbl3JIiXP",
            "track_name": "Love Never Felt so Good"
        },
        {
            "artist_id": "05sIdEkXAYDbDDdv3T56Oj",
            "artist_name": "The Chiffons",
            "popularity": 65,
            "preview_url": "https://p.scdn.co/mp3-preview/175023622bedea5e519cd88ab41e4a4996952a68",
            "track_id": "6vcG9EgeqJUSmmF65lxUm6",
            "track_name": "One Fine Day"
        },
        {
            "artist_id": "3Y3xIwWyq5wnNHPp5gPjOW",
            "artist_name": "Kenny Loggins",
            "popularity": 50,
            "preview_url": "https://p.scdn.co/mp3-preview/6e4a53df67943f56e7c93c3f31473c2b355ca090",
            "track_id": "6bkOMcBuSjl2cftYa2DrFj",
            "track_name": "Celebrate Me Home"
        }
    ]
}